smartcli/__init__.py
smartcli/cli.py
smartcli/config.py
smartcli/templates.py
smartcli/utils.py
smartcli/management/__init__.py
smartcli/management/commands/__init__.py
smartcli/management/commands/create_factory.py
smartcli/management/commands/create_model.py
smartcli/management/commands/create_module.py
smartcli/management/commands/create_serializer.py
smartcli/management/commands/create_service.py
smartcli/management/commands/create_views.py
smartcli/management/commands/test.py
django_smartcli-0.2.0.dist-info/METADATA
django_smartcli-0.2.0.dist-info/WHEEL
django_smartcli-0.2.0.dist-info/entry_points.txt
django_smartcli-0.2.0.dist-info/top_level.txt
django_smartcli-0.2.0.dist-info/RECORD
