Metadata-Version: 2.4
Name: django-smartcli
Version: 0.2.0
Summary: A smart CLI for Django to help you create and manage microservices with consistent architecture
Home-page: https://github.com/nathanrenard3/django-smartcli
Author: Nathan Renard
Author-email: nathan.renard@example.com
License: MIT
Project-URL: Bug Reports, https://github.com/nathanrenard3/django-smartcli/issues
Project-URL: Source, https://github.com/nathanrenard3/django-smartcli
Project-URL: Documentation, https://github.com/nathanrenard3/django-smartcli#readme
Keywords: django,cli,code-generation,microservices,rest-api,django-rest-framework,factory-boy,testing,scaffolding,boilerplate
Classifier: Development Status :: 4 - Beta
Classifier: Intended Audience :: Developers
Classifier: Operating System :: OS Independent
Classifier: Programming Language :: Python :: 3
Classifier: Programming Language :: Python :: 3.8
Classifier: Programming Language :: Python :: 3.9
Classifier: Programming Language :: Python :: 3.10
Classifier: Programming Language :: Python :: 3.11
Classifier: Programming Language :: Python :: 3.12
Classifier: Framework :: Django
Classifier: Framework :: Django :: 4.2
Classifier: Framework :: Django :: 5.0
Classifier: Framework :: Django :: 5.1
Classifier: Framework :: Django :: 5.2
Classifier: Topic :: Software Development :: Libraries :: Python Modules
Classifier: Topic :: Software Development :: Code Generators
Classifier: Topic :: Internet :: WWW/HTTP :: Dynamic Content
Requires-Python: >=3.8
Requires-Dist: Django<5.3,>=4.2
Requires-Dist: djangorestframework>=3.14.0
Requires-Dist: factory-boy>=3.3.0
Provides-Extra: dev
Requires-Dist: pytest>=7.0.0; extra == "dev"
Requires-Dist: pytest-django>=4.5.0; extra == "dev"
Requires-Dist: black>=23.0.0; extra == "dev"
Requires-Dist: flake8>=6.0.0; extra == "dev"
Requires-Dist: mypy>=1.0.0; extra == "dev"
Provides-Extra: test
Requires-Dist: pytest>=7.0.0; extra == "test"
Requires-Dist: pytest-django>=4.5.0; extra == "test"
Requires-Dist: pytest-cov>=4.0.0; extra == "test"
Dynamic: author
Dynamic: author-email
Dynamic: classifier
Dynamic: description
Dynamic: description-content-type
Dynamic: home-page
Dynamic: keywords
Dynamic: license
Dynamic: project-url
Dynamic: provides-extra
Dynamic: requires-dist
Dynamic: requires-python
Dynamic: summary
